{"cameraMode":{"drawMode":0,"name":"Shaded","section":"Shading Mode"},"sceneLighting":true,"audioPlay":false,"sceneViewState":{"showFog":true,"showMaterialUpdate":false,"showSkybox":true,"showFlares":true,"showImageEffects":true,"showParticleSystems":true},"in2DMode":false,"pivot":{"x":430.8580322265625,"y":105.7479248046875,"z":314.7372131347656},"rotation":{"x":-0.09449753910303116,"y":0.18465770781040193,"z":-0.01784018985927105,"w":-0.9780866503715515},"size":43.584468841552737,"orthographic":false}